ch_anime/__init__.py
ch_anime/spyder.py
ch_anime-0.1.1.dist-info/METADATA
ch_anime-0.1.1.dist-info/WHEEL
ch_anime-0.1.1.dist-info/top_level.txt
ch_anime-0.1.1.dist-info/RECORD
