Metadata-Version: 2.1
Name: ch-anime
Version: 0.1.1
Summary: some spider
Home-page: https://github.com/phillychi3/ch_anime
Author: phillychi3
Author-email: phillychi3@gmail.com
License: UNKNOWN
Platform: UNKNOWN
Classifier: Programming Language :: Python :: 3
Classifier: License :: OSI Approved :: Apache Software License
Classifier: Operating System :: OS Independent
